<?xml version="1.0" encoding="utf-8" ?>
<Strings>
    <DefaultLocale>en_US</DefaultLocale>
    <en_US>
		<InvalidArg>Invalid argument - {0} {1}</InvalidArg>
		<NDCFormat> is not a valid NDC.  It must be an 11 digit number that is not 00000000000.</NDCFormat>
		<GPI14Characters>must be 14 characters.</GPI14Characters>
		<GreaterThanEqualZero>must be greater than or equal to zero.</GreaterThanEqualZero>
		<GreaterThanZero>must be greater than zero.</GreaterThanZero>
		<NotAvailable>{0} not available for this {1}.</NotAvailable>
		<NotEmpty>must not be empty.</NotEmpty>
		<NullValue>Null value encountered - {0}.</NullValue>
		<Required>required.</Required>
		<ValidValue>must be a valid value.</ValidValue>
		<ValueLessThanZero>The value of {0} cannot be less than zero.</ValueLessThanZero>
		<ValueNotFound>Value not found - {0}.</ValueNotFound>
		<ValueNotSupplied>A value for {0} must be entered.</ValueNotSupplied>		
        <NoConstraint>No constraint found for {0}</NoConstraint>
        <CannotConvertType>The value, {0}, cannot be converted to type of {1}.</CannotConvertType>
        <InvalidValue>The value, '{0}', is not allowed.  Valid values </InvalidValue>
        <MinExclusive>The value, {0}, is less than or equal to the allowed minimum value of {1}.</MinExclusive>
        <MinInclusive>The value, {0}, is less than the allowed minimum value of {1}.</MinInclusive>
        <MaxExclusive>The value, {0}, is greater than or equal to the allowed maximum value of {1}.</MaxExclusive>
        <MaxInclusive>The value, {0}, is greater than the allowed maximum value of {1}.</MaxInclusive>
        <MinLength>The value, {0}, is less than the allowed minimum length of {1}.</MinLength>
        <MaxLength>The value, {0}, is greater than the allowed maximum length of {1}.</MaxLength>        
		<InvalidArg>Invalid argument - {0} {1}</InvalidArg>
		<InvalidTransformParameter> is not a valid transform parameter.</InvalidTransformParameter>
		<NotNull>must not be null.</NotNull>
		<NoDataType>No data type specified for the constraint {0}.</NoDataType>
		<AttributeNameRequired>A name is required for all schema attributes.</AttributeNameRequired>
    </en_US>
</Strings>