<?xml version="1.0"?>
<MediSpan.IREF>
    <IMM>
        <ContentDir>c://your_path//</ContentDir>
        <PrerenderInputFilename>c://your_path//your_file.txt</PrerenderInputFilename>
        <PrerenderOutputDir>c://your_path//</PrerenderOutputDir>
        <TransformParamsXSDFilename>Medispan.IREF.IMM.RenderParam.xsd</TransformParamsXSDFilename>
	<XSLFilename>imm.xsl</XSLFilename>
        <XMLXSLFilename>immxml.xsl</XMLXSLFilename>
        <XSLFOFilename>immfo.xsl</XSLFOFilename>
    </IMM>
</MediSpan.IREF>